README.txt
setup.py
affinitic/__init__.py
affinitic.docpyflakes.egg-info/PKG-INFO
affinitic.docpyflakes.egg-info/SOURCES.txt
affinitic.docpyflakes.egg-info/dependency_links.txt
affinitic.docpyflakes.egg-info/entry_points.txt
affinitic.docpyflakes.egg-info/namespace_packages.txt
affinitic.docpyflakes.egg-info/not-zip-safe
affinitic.docpyflakes.egg-info/requires.txt
affinitic.docpyflakes.egg-info/top_level.txt
affinitic/docpyflakes/__init__.py
affinitic/docpyflakes/docpyflakes.py
docs/HISTORY.txt