Metadata-Version: 1.0
Name: affinitic.docpyflakes
Version: 0.1
Summary: Pyflakes your doctest
Home-page: http://svn.affinitic.be/python/affinitic.docpyflakes
Author: Affinitic
Author-email: jfroche@affinitic.be
License: GPL
Platform: UNKNOWN
Classifier: Programming Language :: Python
Classifier: Topic :: Software Development
Classifier: Topic :: Utilities
Classifier: Programming Language :: Python
